tic_tac_toe.v
`timescale 1ns/1ps

module tic_tac_toe(
    input wire clk,
    input wire rst_n,
    input wire [3:0] move_idx,
    input wire move_en,
    output reg [17:0] board_out,
    output reg turn,
    output reg invalid_move,
    output reg [1:0] winner
);

    reg [1:0] board [0:8];
    integer i;
    reg [1:0] win_detected;
    reg winner_locked;
    reg [3:0] filled_count;

    // --- Check win condition (combinational)
    always @(*) begin
        win_detected = 2'b00;
        if (board[0]!=2'b00 && board[0]==board[1] && board[1]==board[2]) win_detected = board[0];
        else if (board[3]!=2'b00 && board[3]==board[4] && board[4]==board[5]) win_detected = board[3];
        else if (board[6]!=2'b00 && board[6]==board[7] && board[7]==board[8]) win_detected = board[6];
        else if (board[0]!=2'b00 && board[0]==board[3] && board[3]==board[6]) win_detected = board[0];
        else if (board[1]!=2'b00 && board[1]==board[4] && board[4]==board[7]) win_detected = board[1];
        else if (board[2]!=2'b00 && board[2]==board[5] && board[5]==board[8]) win_detected = board[2];
        else if (board[0]!=2'b00 && board[0]==board[4] && board[4]==board[8]) win_detected = board[0];
        else if (board[2]!=2'b00 && board[2]==board[4] && board[4]==board[6]) win_detected = board[2];
    end

    // --- Sequential logic
    always @(posedge clk or negedge rst_n) begin
        if (!rst_n) begin
            for (i = 0; i < 9; i = i + 1)
                board[i] <= 2'b00;
            turn <= 1'b1;
            invalid_move <= 0;
            winner <= 2'b00;
            winner_locked <= 0;
            filled_count <= 0;
            board_out <= 18'b0;
        end else begin
            invalid_move <= 0;

            // Detect winner
            if (!winner_locked) begin
                if (win_detected == 2'b01) begin
                    winner <= 2'b01; winner_locked <= 1;
                end else if (win_detected == 2'b10) begin
                    winner <= 2'b10; winner_locked <= 1;
                end else begin
                    winner <= 2'b00;
                end
            end

            // Handle move
            if (move_en) begin
                if (winner_locked || move_idx > 8) begin
                    invalid_move <= 1;
                end else if (board[move_idx] == 2'b00) begin
                    board[move_idx] <= turn ? 2'b01 : 2'b10;
                    filled_count <= filled_count + 1;
                    turn <= ~turn;
                end else begin
                    invalid_move <= 1;
                end
            end

            // Draw check
            if (!winner_locked && filled_count == 9) begin
                winner <= 2'b11;
                winner_locked <= 1;
            end

            // Pack board for waveform
            board_out <= {
                board[8], board[7], board[6],
                board[5], board[4], board[3],
                board[2], board[1], board[0]
            };
        end
    end

endmodule

tb_tic_tac_toe.v
`timescale 1ns/1ps

module tb_tic_tac_toe;

    reg clk = 0;
    reg rst_n = 0;
    reg [3:0] move_idx;
    reg move_en;
    wire [17:0] board_out;
    wire turn;
    wire invalid_move;
    wire [1:0] winner;

    tic_tac_toe dut (
        .clk(clk),
        .rst_n(rst_n),
        .move_idx(move_idx),
        .move_en(move_en),
        .board_out(board_out),
        .turn(turn),
        .invalid_move(invalid_move),
        .winner(winner)
    );

    always #5 clk = ~clk;

    task do_move;
        input [3:0] idx;
        begin
            @(negedge clk);
            move_idx = idx;
            move_en = 1;
            @(negedge clk);
            move_en = 0;
            #1;
            $display("%0t ns | Move=%0d | Turn=%b | Invalid=%b | Winner=%b | Board=%b",
                     $time, idx, turn, invalid_move, winner, board_out);
        end
    endtask

    initial begin
        $dumpfile("tic_tac_toe.vcd");
        $dumpvars(0, tb_tic_tac_toe);

        rst_n = 0; #20; rst_n = 1; #10;

        $display("=== GAME 1: X Wins on Top Row ===");
        do_move(0);
        do_move(3);
        do_move(1);
        do_move(4);
        do_move(2);

        #30;
        $display("Attempt invalid move after win:");
        do_move(5);

        #40;
        $display("=== GAME 2: Draw ===");
        rst_n = 0; #20; rst_n = 1; #10;

        do_move(0);
        do_move(1);
        do_move(2);
        do_move(4);
        do_move(3);
        do_move(5);
        do_move(7);
        do_move(6);
        do_move(8);

        #50;
        $display("Simulation complete. Winner=%b", winner);
        $finish;
    end

endmodule

tic_tac_toe.vcd
$date
	Sun Nov  9 12:28:24 2025
$end
$version
	Icarus Verilog
$end
$timescale
	1ps
$end
$scope module tb_tic_tac_toe $end
$var wire 2 ! winner [1:0] $end
$var wire 1 " turn $end
$var wire 1 # invalid_move $end
$var wire 18 $ board_out [17:0] $end
$var reg 1 % clk $end
$var reg 1 & move_en $end
$var reg 4 ' move_idx [3:0] $end
$var reg 1 ( rst_n $end
$scope module dut $end
$var wire 1 % clk $end
$var wire 1 & move_en $end
$var wire 4 ) move_idx [3:0] $end
$var wire 1 ( rst_n $end
$var reg 18 * board_out [17:0] $end
$var reg 4 + filled_count [3:0] $end
$var reg 1 # invalid_move $end
$var reg 1 " turn $end
$var reg 2 , win_detected [1:0] $end
$var reg 2 - winner [1:0] $end
$var reg 1 . winner_locked $end
$var integer 32 / i [31:0] $end
$upscope $end
$scope task do_move $end
$var reg 4 0 idx [3:0] $end
$upscope $end
$upscope $end
$enddefinitions $end
$comment Show the parameter values. $end
$dumpall
$end
#0
$dumpvars
bx 0
b1001 /
0.
b0 -
b0 ,
b0 +
b0 *
bx )
0(
bx '
x&
0%
b0 $
0#
1"
b0 !
$end
#5000
b1001 /
1%
#10000
0%
#15000
b1001 /
1%
#20000
0%
1(
#25000
1%
#30000
1&
b0 '
b0 )
0%
b0 0
#35000
0"
b1 +
1%
#40000
0&
0%
#41000
b11 0
#45000
b1 $
b1 *
1%
#50000
1&
b11 '
b11 )
0%
#55000
1"
b10 +
1%
#60000
0&
0%
#61000
b1 0
#65000
b10000001 $
b10000001 *
1%
#70000
1&
b1 '
b1 )
0%
#75000
0"
b11 +
1%
#80000
0&
0%
#81000
b100 0
#85000
b10000101 $
b10000101 *
1%
#90000
1&
b100 '
b100 )
0%
#95000
1"
b100 +
1%
#100000
0&
0%
#101000
b10 0
#105000
b1010000101 $
b1010000101 *
1%
#110000
1&
b10 '
b10 )
0%
#115000
b1 ,
0"
b101 +
1%
#120000
0&
0%
#125000
b1010010101 $
b1010010101 *
1.
b1 !
b1 -
1%
#130000
0%
#135000
1%
#140000
0%
#145000
1%
#150000
0%
#151000
b101 0
#155000
1%
#160000
1&
b101 '
b101 )
0%
#165000
1#
1%
#170000
0&
0%
#175000
0#
1%
#180000
0%
#185000
1%
#190000
0%
#195000
1%
#200000
0%
#205000
1%
#210000
0%
#211000
b0 ,
b0 $
b0 *
b0 +
0.
b0 !
b0 -
1"
b1001 /
0(
#215000
b1001 /
1%
#220000
0%
#225000
b1001 /
1%
#230000
0%
#231000
1(
#235000
1%
#240000
0%
#241000
b0 0
#245000
1%
#250000
1&
b0 '
b0 )
0%
#255000
0"
b1 +
1%
#260000
0&
0%
#261000
b1 0
#265000
b1 $
b1 *
1%
#270000
1&
b1 '
b1 )
0%
#275000
1"
b10 +
1%
#280000
0&
0%
#281000
b10 0
#285000
b1001 $
b1001 *
1%
#290000
1&
b10 '
b10 )
0%
#295000
0"
b11 +
1%
#300000
0&
0%
#301000
b100 0
#305000
b11001 $
b11001 *
1%
#310000
1&
b100 '
b100 )
0%
#315000
1"
b100 +
1%
#320000
0&
0%
#321000
b11 0
#325000
b1000011001 $
b1000011001 *
1%
#330000
1&
b11 '
b11 )
0%
#335000
0"
b101 +
1%
#340000
0&
0%
#341000
b101 0
#345000
b1001011001 $
b1001011001 *
1%
#350000
1&
b101 '
b101 )
0%
#355000
1"
b110 +
1%
#360000
0&
0%
#361000
b111 0
#365000
b101001011001 $
b101001011001 *
1%
#370000
1&
b111 '
b111 )
0%
#375000
0"
b111 +
1%
#380000
0&
0%
#381000
b110 0
#385000
b100101001011001 $
b100101001011001 *
1%
#390000
1&
b110 '
b110 )
0%
#395000
1"
b1000 +
1%
#400000
0&
0%
#401000
b1000 0
#405000
b110101001011001 $
b110101001011001 *
1%
#410000
1&
b1000 '
b1000 )
0%
#415000
0"
b1001 +
1%
#420000
0&
0%
#425000
b10110101001011001 $
b10110101001011001 *
1.
b11 !
b11 -
1%
